LICENCE
MANIFEST.in
README.md
pyproject.toml
requirements.txt
setup.cfg
src/cbadc/__init__.py
src/cbadc/__version__.py
src/cbadc/analog_frontend.py
src/cbadc/fom.py
src/cbadc/utilities.py
src/cbadc.egg-info/PKG-INFO
src/cbadc.egg-info/SOURCES.txt
src/cbadc.egg-info/dependency_links.txt
src/cbadc.egg-info/requires.txt
src/cbadc.egg-info/top_level.txt
src/cbadc.egg-info/zip-safe
src/cbadc/analog_signal/__init__.py
src/cbadc/analog_signal/_analog_signal.py
src/cbadc/analog_signal/clock.py
src/cbadc/analog_signal/constant_signal.py
src/cbadc/analog_signal/impulse_responses.py
src/cbadc/analog_signal/quadrature.py
src/cbadc/analog_signal/ramp.py
src/cbadc/analog_signal/sinc_pulse.py
src/cbadc/analog_signal/sinusoidal.py
src/cbadc/analog_signal/zero_order_hold.py
src/cbadc/analog_system/__init__.py
src/cbadc/analog_system/analog_system.py
src/cbadc/analog_system/chain_of_integrators.py
src/cbadc/analog_system/filters.py
src/cbadc/analog_system/leap_frog.py
src/cbadc/analog_system/modulator.py
src/cbadc/analog_system/topology.py
src/cbadc/circuit/__init__.py
src/cbadc/circuit/analog_frontend.py
src/cbadc/circuit/digital_control.py
src/cbadc/circuit/lc_tank.py
src/cbadc/circuit/opamp.py
src/cbadc/circuit/ota.py
src/cbadc/circuit/simulator.py
src/cbadc/circuit/state_space.py
src/cbadc/circuit/testbench.py
src/cbadc/circuit/components/__init__.py
src/cbadc/circuit/components/analog_delay.py
src/cbadc/circuit/components/comparator.py
src/cbadc/circuit/components/integrator.py
src/cbadc/circuit/components/observer.py
src/cbadc/circuit/components/opamp.py
src/cbadc/circuit/components/ota.py
src/cbadc/circuit/components/passives.py
src/cbadc/circuit/components/reference_source.py
src/cbadc/circuit/components/sources.py
src/cbadc/circuit/components/summer.py
src/cbadc/circuit/components/vcvs.py
src/cbadc/circuit/components/voltage_buffer.py
src/cbadc/circuit/models/__init__.py
src/cbadc/circuit/models/analog_delay.py
src/cbadc/circuit/models/comparator.py
src/cbadc/circuit/models/integrator.py
src/cbadc/circuit/models/observer.py
src/cbadc/circuit/models/ota.py
src/cbadc/circuit/models/reference_source.py
src/cbadc/circuit/models/summer.py
