Metadata-Version: 2.1
Name: cbadc
Version: 0.3.2
Summary: A toolbox for simulating control-bounded converters.
Home-page: https://github.com/hammal/cbadc
Author: Hampus Malmberg
Author-email: hampus.malmberg88@gmail.com
Project-URL: Bug Tracker, https://github.com/hammal/cbadc/issues
Classifier: Programming Language :: Python :: 3
Classifier: License :: OSI Approved :: GNU General Public License v3 (GPLv3)
Classifier: Operating System :: OS Independent
Requires-Python: >=3.9
License-File: LICENCE
Requires-Dist: numpy>=1.24.4
Requires-Dist: scipy>=1.10.1
Requires-Dist: tqdm>=4.61.0
Requires-Dist: requests>=2.25.1
Requires-Dist: typing-extensions
Requires-Dist: pandas>=1.4.1
Requires-Dist: jinja2>=3
Requires-Dist: matplotlib>=3.5.1
Requires-Dist: sympy>=1.9
Requires-Dist: mpmath>=1.1
Requires-Dist: ltspice>=1.0.6
Requires-Dist: tensorflow>=2.14.0
